orchard_bouman/__init__.py
orchard_bouman/orchard_bouman.py
orchard_bouman-1.0.1.dist-info/LICENSE
orchard_bouman-1.0.1.dist-info/METADATA
orchard_bouman-1.0.1.dist-info/WHEEL
orchard_bouman-1.0.1.dist-info/top_level.txt
orchard_bouman-1.0.1.dist-info/RECORD
