Metadata-Version: 2.1
Name: orchard-bouman
Version: 1.0.1
Summary: Python implementation of Orchard Bouman clustering using NumPy
Author-email: Brandon Hastings <bhastings23320@gmail.com>
License: GNU GENERAL PUBLIC LICENSE
Project-URL: Homepage, https://github.com/brandon-hastings/orchard_bouman
Keywords: color quantization,image clustering,orchard bouman
Classifier: Programming Language :: Python
Requires-Python: >=3.10
License-File: LICENSE
Requires-Dist: numpy>=1.26.4
